or_models/SCP.py
or_models/__init__.py
tests/__init__.py
or_models-0.1.1.1.dist-info/LICENSE
or_models-0.1.1.1.dist-info/METADATA
or_models-0.1.1.1.dist-info/WHEEL
or_models-0.1.1.1.dist-info/top_level.txt
or_models-0.1.1.1.dist-info/RECORD
