Metadata-Version: 2.1
Name: or-models
Version: 0.1.1.1
Summary: Some standard textbook Optimization Models and Algorithms.
Home-page: https://github.com/hak91/OptimizationModels
Author: Hussain Kharodawala
Author-email: hussain.abbas52@gmail.com
License: UNKNOWN
Keywords: set cover,Operations Research,Mathematical Optimization,heuristic,greedy,Lagrangian Relaxation
Platform: UNKNOWN
Classifier: Programming Language :: Python :: 3.6
Classifier: Programming Language :: Python :: 3.8
Requires-Dist: numpy (>=1.19.2)
Requires-Dist: ortools (>=8.2.8710)
